gh_contributors.py
gh_contributors-0.1.0.dist-info/DESCRIPTION.rst
gh_contributors-0.1.0.dist-info/METADATA
gh_contributors-0.1.0.dist-info/RECORD
gh_contributors-0.1.0.dist-info/WHEEL
gh_contributors-0.1.0.dist-info/entry_points.txt
gh_contributors-0.1.0.dist-info/metadata.json
gh_contributors-0.1.0.dist-info/top_level.txt
