Metadata-Version: 2.0
Name: gh-contributors
Version: 0.1.0
Summary: Generate contributors.md via the command line
Home-page: https://github.com/chenjiandongx/gh-contributors
Author: chenjiandongx
Author-email: chenjiandongx@qq.com
License: MIT
Platform: UNKNOWN
